{
  "last_updated": "2026-05-11T17:31:48Z",
  "servers": [
    {
  "name": "NIPA_server",
  "type": "gpu",
  "status": "online",
  "timestamp": "2026-05-11T17:31:48Z",
  "gpu_count": 1,
  "gpu_memory_gb": 80,
  "gpus": [{"index":0,"name":"NVIDIA H100 80GB HBM3","utilization":100,"memory_used_mb":28945,"memory_total_mb":81559,"temperature":40}],
  "cpu": {"cores": 24, "load_avg": 9.75, "usage_percent": 21.6},
  "memory": {"used_mb": 23770, "total_mb": 241600, "percent": 9.8},
  "disk": {"used": "761G", "total": "993G", "percent": 77},
  "users": ["ispl"],
  "gpu_processes": [{"pid":2684188,"name":"python","memory_mb":4588},{"pid":2715764,"name":"/home/ispl/anaconda3/envs/scaffold_gs/bin/DH_APGS_v00_LITE_drj","memory_mb":6984},{"pid":2741158,"name":"python","memory_mb":6526},{"pid":2765269,"name":"/home/ispl/anaconda3/envs/pnm_ugs/bin/DH_FuseGS_v01c_bns","memory_mb":520},{"pid":2790952,"name":"python","memory_mb":4558},{"pid":2801054,"name":"/home/ispl/anaconda3/envs/gs_original_hb/bin/DH_CRGS_v01","memory_mb":5730}]
},
    {
  "name": "ISPL",
  "type": "gpu",
  "status": "online",
  "timestamp": "2026-05-11T17:31:48Z",
  "gpu_count": 8,
  "gpu_memory_gb": 48,
  "gpus": [{"index":0,"name":"NVIDIA RTX A6000","utilization":0,"memory_used_mb":3160,"memory_total_mb":49140,"temperature":42},{"index":1,"name":"NVIDIA RTX A6000","utilization":0,"memory_used_mb":8279,"memory_total_mb":49140,"temperature":44},{"index":2,"name":"NVIDIA RTX A6000","utilization":0,"memory_used_mb":10,"memory_total_mb":49140,"temperature":31},{"index":3,"name":"NVIDIA RTX A6000","utilization":0,"memory_used_mb":10,"memory_total_mb":49140,"temperature":32},{"index":4,"name":"NVIDIA RTX A6000","utilization":0,"memory_used_mb":10,"memory_total_mb":49140,"temperature":32},{"index":5,"name":"NVIDIA RTX A6000","utilization":0,"memory_used_mb":10,"memory_total_mb":49140,"temperature":33},{"index":6,"name":"NVIDIA RTX A6000","utilization":0,"memory_used_mb":10,"memory_total_mb":49140,"temperature":29},{"index":7,"name":"NVIDIA RTX A6000","utilization":0,"memory_used_mb":10,"memory_total_mb":49140,"temperature":28}],
  "cpu": {"cores": 48, "load_avg": 66.95, "usage_percent": 29.8},
  "memory": {"used_mb": 75200, "total_mb": 709363, "percent": 10.6},
  "disk": {"used": "1.8T", "total": "3.6T", "percent": 52},
  "users": ["ispl"],
  "gpu_processes": [{"pid":1839290,"name":"/home/ispl/anaconda3/envs/dongho-mip-splatting/bin/python","memory_mb":1720},{"pid":1839291,"name":"/home/ispl/anaconda3/envs/dongho-mip-splatting/bin/python","memory_mb":1614},{"pid":1834626,"name":"python","memory_mb":8010}]
},
    {
  "name": "CPU1",
  "type": "cpu",
  "status": "online",
  "timestamp": "2026-05-11T17:31:48Z",
  "cpu": {"cores": 64, "load_avg": 0.08, "usage_percent": 0.1},
  "memory": {"used_mb": 4444, "total_mb": 773344, "percent": 0.6},
  "disk": {"used": "35G", "total": "879G", "percent": 5},
  "users": []
},
    {
  "name": "CPU2",
  "type": "cpu",
  "status": "online",
  "timestamp": "2026-05-11T17:31:48Z",
  "cpu": {"cores": 64, "load_avg": 0.04, "usage_percent": 0.2},
  "memory": {"used_mb": 6205, "total_mb": 773344, "percent": 0.8},
  "disk": {"used": "46G", "total": "879G", "percent": 6},
  "users": ["user"]
},
    {
  "name": "CPU3",
  "type": "cpu",
  "status": "online",
  "timestamp": "2026-05-11T17:31:48Z",
  "cpu": {"cores": 64, "load_avg": 0.08, "usage_percent": 0.1},
  "memory": {"used_mb": 3895, "total_mb": 773344, "percent": 0.5},
  "disk": {"used": "33G", "total": "879G", "percent": 4},
  "users": ["user"]
},
    {
  "name": "CPU4",
  "type": "cpu",
  "status": "online",
  "timestamp": "2026-05-11T17:31:48Z",
  "cpu": {"cores": 64, "load_avg": 45.06, "usage_percent": 70.4},
  "memory": {"used_mb": 64397, "total_mb": 773344, "percent": 8.3},
  "disk": {"used": "162G", "total": "879G", "percent": 20},
  "users": ["user"]
}
  ]
}
