{
  "last_updated": "2026-05-31T08:45:32Z",
  "servers": [
    {
  "name": "NIPA_server",
  "type": "gpu",
  "status": "online",
  "timestamp": "2026-05-31T08:45:32Z",
  "gpu_count": 1,
  "gpu_memory_gb": 80,
  "gpus": [{"index":0,"name":"NVIDIA H100 80GB HBM3","utilization":84,"memory_used_mb":24425,"memory_total_mb":81559,"temperature":45}],
  "cpu": {"cores": 24, "load_avg": 4.03, "usage_percent": 12.6},
  "memory": {"used_mb": 36657, "total_mb": 241600, "percent": 15.2},
  "disk": {"used": "913G", "total": "993G", "percent": 93},
  "users": ["ispl"],
  "gpu_processes": [{"pid":1799876,"name":"/home/ispl/anaconda3/envs/hac_plus/bin/APGS_voxel","memory_mb":13538},{"pid":2235474,"name":"python","memory_mb":10872}]
},
    {
  "name": "ISPL",
  "type": "gpu",
  "status": "online",
  "timestamp": "2026-05-31T08:45:32Z",
  "gpu_count": 8,
  "gpu_memory_gb": 48,
  "gpus": [{"index":0,"name":"NVIDIA RTX A6000","utilization":0,"memory_used_mb":12,"memory_total_mb":49140,"temperature":42},{"index":1,"name":"NVIDIA RTX A6000","utilization":1,"memory_used_mb":16041,"memory_total_mb":49140,"temperature":42},{"index":2,"name":"NVIDIA RTX A6000","utilization":0,"memory_used_mb":383,"memory_total_mb":49140,"temperature":48},{"index":3,"name":"NVIDIA RTX A6000","utilization":0,"memory_used_mb":10,"memory_total_mb":49140,"temperature":51},{"index":4,"name":"NVIDIA RTX A6000","utilization":0,"memory_used_mb":383,"memory_total_mb":49140,"temperature":46},{"index":5,"name":"NVIDIA RTX A6000","utilization":0,"memory_used_mb":945,"memory_total_mb":49140,"temperature":49},{"index":6,"name":"NVIDIA RTX A6000","utilization":0,"memory_used_mb":22351,"memory_total_mb":49140,"temperature":49},{"index":7,"name":"NVIDIA RTX A6000","utilization":0,"memory_used_mb":12,"memory_total_mb":49140,"temperature":39}],
  "cpu": {"cores": 48, "load_avg": 50.99, "usage_percent": 37.7},
  "memory": {"used_mb": 165491, "total_mb": 709363, "percent": 23.3},
  "disk": {"used": "2.8T", "total": "3.6T", "percent": 81},
  "users": ["ispl"],
  "gpu_processes": [{"pid":1333029,"name":"/home/ispl/anaconda3/envs/amgs_mip/bin/python","memory_mb":16026},{"pid":1348732,"name":"/home/ispl/anaconda3/envs/amgs_mip/bin/python","memory_mb":368},{"pid":1347731,"name":"/home/ispl/anaconda3/envs/amgs_mip/bin/python","memory_mb":368},{"pid":1350584,"name":"/home/ispl/anaconda3/envs/amgs_mip/bin/python","memory_mb":1462},{"pid":1331726,"name":"/home/ispl/anaconda3/envs/amgs_mip/bin/python","memory_mb":22336},{"pid":1348895,"name":"/home/ispl/anaconda3/envs/amgs_mip/bin/python","memory_mb":10}]
},
    {
  "name": "CPU1",
  "type": "cpu",
  "status": "online",
  "timestamp": "2026-05-31T08:45:32Z",
  "cpu": {"cores": 64, "load_avg": 0.17, "usage_percent": 0.0},
  "memory": {"used_mb": 7738, "total_mb": 773344, "percent": 1.0},
  "disk": {"used": "36G", "total": "879G", "percent": 5},
  "users": ["user"]
},
    {
  "name": "CPU2",
  "type": "cpu",
  "status": "online",
  "timestamp": "2026-05-31T08:45:32Z",
  "cpu": {"cores": 64, "load_avg": 0.30, "usage_percent": 0.2},
  "memory": {"used_mb": 6879, "total_mb": 773344, "percent": 0.9},
  "disk": {"used": "47G", "total": "879G", "percent": 6},
  "users": ["user"]
},
    {
  "name": "CPU3",
  "type": "cpu",
  "status": "online",
  "timestamp": "2026-05-31T08:45:32Z",
  "cpu": {"cores": 64, "load_avg": 0.07, "usage_percent": 0.0},
  "memory": {"used_mb": 4936, "total_mb": 773344, "percent": 0.6},
  "disk": {"used": "37G", "total": "879G", "percent": 5},
  "users": ["user"]
},
    {
  "name": "CPU4",
  "type": "cpu",
  "status": "online",
  "timestamp": "2026-05-31T08:45:32Z",
  "cpu": {"cores": 64, "load_avg": 14.05, "usage_percent": 22.3},
  "memory": {"used_mb": 37624, "total_mb": 773344, "percent": 4.9},
  "disk": {"used": "161G", "total": "879G", "percent": 20},
  "users": ["user"]
}
  ]
}
