{
  "last_updated": "2026-04-13T06:06:01Z",
  "servers": [
    {
  "name": "NIPA_server",
  "type": "gpu",
  "status": "online",
  "timestamp": "2026-04-13T06:06:01Z",
  "gpu_count": 1,
  "gpu_memory_gb": 80,
  "gpus": [{"index":0,"name":"NVIDIA H100 80GB HBM3","utilization":100,"memory_used_mb":54749,"memory_total_mb":81559,"temperature":49}],
  "cpu": {"cores": 24, "load_avg": 7.72, "usage_percent": 29.9},
  "memory": {"used_mb": 16545, "total_mb": 241600, "percent": 6.8},
  "disk": {"used": "564G", "total": "993G", "percent": 57},
  "users": [],
  "gpu_processes": [{"pid":23077,"name":"python","memory_mb":9554},{"pid":32745,"name":"/home/ispl/anaconda3/envs/propose_0_TH/bin/python","memory_mb":9502},{"pid":34479,"name":"python","memory_mb":9390},{"pid":48369,"name":"python","memory_mb":8604},{"pid":50694,"name":"python","memory_mb":3928},{"pid":53578,"name":"python","memory_mb":13732}]
},
    {
  "name": "ISPL",
  "type": "gpu",
  "status": "online",
  "timestamp": "2026-04-13T06:06:01Z",
  "gpu_count": 8,
  "gpu_memory_gb": 48,
  "gpus": [{"index":0,"name":"NVIDIA RTX A6000","utilization":0,"memory_used_mb":3402,"memory_total_mb":49140,"temperature":34},{"index":1,"name":"NVIDIA RTX A6000","utilization":0,"memory_used_mb":10,"memory_total_mb":49140,"temperature":26},{"index":2,"name":"NVIDIA RTX A6000","utilization":0,"memory_used_mb":30969,"memory_total_mb":49140,"temperature":37},{"index":3,"name":"NVIDIA RTX A6000","utilization":0,"memory_used_mb":6939,"memory_total_mb":49140,"temperature":37},{"index":4,"name":"NVIDIA RTX A6000","utilization":1,"memory_used_mb":3119,"memory_total_mb":49140,"temperature":36},{"index":5,"name":"NVIDIA RTX A6000","utilization":98,"memory_used_mb":13799,"memory_total_mb":49140,"temperature":71},{"index":6,"name":"NVIDIA RTX A6000","utilization":100,"memory_used_mb":40174,"memory_total_mb":49140,"temperature":64},{"index":7,"name":"NVIDIA RTX A6000","utilization":0,"memory_used_mb":10,"memory_total_mb":49140,"temperature":26}],
  "cpu": {"cores": 48, "load_avg": 35.04, "usage_percent": 11.8},
  "memory": {"used_mb": 82543, "total_mb": 709364, "percent": 11.6},
  "disk": {"used": "2.8T", "total": "3.6T", "percent": 83},
  "users": ["ispl"],
  "gpu_processes": [{"pid":2494233,"name":"python","memory_mb":3386},{"pid":3538184,"name":"[Not Found]","memory_mb":30954},{"pid":2551035,"name":"python","memory_mb":6924},{"pid":2555798,"name":"python","memory_mb":3472},{"pid":2475796,"name":"python","memory_mb":13784},{"pid":2138786,"name":"python","memory_mb":6690},{"pid":2138787,"name":"python","memory_mb":6692},{"pid":2138785,"name":"python","memory_mb":6690},{"pid":2138794,"name":"python","memory_mb":6690},{"pid":2138796,"name":"python","memory_mb":6692},{"pid":2138784,"name":"python","memory_mb":6690}]
},
    {
  "name": "CPU1",
  "type": "cpu",
  "status": "online",
  "timestamp": "2026-04-13T06:06:01Z",
  "cpu": {"cores": 64, "load_avg": 0.15, "usage_percent": 0.1},
  "memory": {"used_mb": 9319, "total_mb": 773344, "percent": 1.2},
  "disk": {"used": "34G", "total": "879G", "percent": 5},
  "users": ["user"]
},
    {
  "name": "CPU2",
  "type": "cpu",
  "status": "online",
  "timestamp": "2026-04-13T06:06:01Z",
  "cpu": {"cores": 64, "load_avg": 0.16, "usage_percent": 0.1},
  "memory": {"used_mb": 5103, "total_mb": 773344, "percent": 0.7},
  "disk": {"used": "45G", "total": "879G", "percent": 6},
  "users": ["user"]
},
    {
  "name": "CPU3",
  "type": "cpu",
  "status": "online",
  "timestamp": "2026-04-13T06:06:01Z",
  "cpu": {"cores": 64, "load_avg": 0.02, "usage_percent": 0.1},
  "memory": {"used_mb": 3822, "total_mb": 773344, "percent": 0.5},
  "disk": {"used": "33G", "total": "879G", "percent": 4},
  "users": ["user"]
},
    {
  "name": "CPU4",
  "type": "cpu",
  "status": "online",
  "timestamp": "2026-04-13T06:06:01Z",
  "cpu": {"cores": 64, "load_avg": 0.00, "usage_percent": 0.1},
  "memory": {"used_mb": 5051, "total_mb": 773344, "percent": 0.7},
  "disk": {"used": "156G", "total": "879G", "percent": 19},
  "users": ["user"]
}
  ]
}
