{
  "last_updated": "2026-05-27T17:15:17Z",
  "servers": [
    {
  "name": "NIPA_server",
  "type": "gpu",
  "status": "online",
  "timestamp": "2026-05-27T17:15:17Z",
  "gpu_count": 1,
  "gpu_memory_gb": 80,
  "gpus": [{"index":0,"name":"NVIDIA H100 80GB HBM3","utilization":100,"memory_used_mb":55186,"memory_total_mb":81559,"temperature":42}],
  "cpu": {"cores": 24, "load_avg": 10.90, "usage_percent": 36.9},
  "memory": {"used_mb": 110112, "total_mb": 241600, "percent": 45.6},
  "disk": {"used": "931G", "total": "993G", "percent": 94},
  "users": ["ispl"],
  "gpu_processes": [{"pid":1898998,"name":"python","memory_mb":2774},{"pid":1900173,"name":"python","memory_mb":3314},{"pid":2054668,"name":"/home/ispl/anaconda3/envs/hac_plus/bin/APGS_voxel","memory_mb":9786},{"pid":2054672,"name":"/home/ispl/anaconda3/envs/hac_plus/bin/APGS_voxel","memory_mb":9722},{"pid":2339176,"name":"APGS_ellipsoid","memory_mb":8842},{"pid":2360446,"name":"python","memory_mb":5100},{"pid":2435941,"name":"APGS_ellipsoid","memory_mb":10144},{"pid":2802878,"name":"python","memory_mb":5454}]
},
    {
  "name": "ISPL",
  "type": "gpu",
  "status": "online",
  "timestamp": "2026-05-27T17:15:17Z",
  "gpu_count": 8,
  "gpu_memory_gb": 48,
  "gpus": [{"index":0,"name":"NVIDIA RTX A6000","utilization":0,"memory_used_mb":5539,"memory_total_mb":49140,"temperature":38},{"index":1,"name":"NVIDIA RTX A6000","utilization":0,"memory_used_mb":515,"memory_total_mb":49140,"temperature":35},{"index":2,"name":"NVIDIA RTX A6000","utilization":33,"memory_used_mb":15329,"memory_total_mb":49140,"temperature":53},{"index":3,"name":"NVIDIA RTX A6000","utilization":97,"memory_used_mb":12065,"memory_total_mb":49140,"temperature":74},{"index":4,"name":"NVIDIA RTX A6000","utilization":95,"memory_used_mb":11515,"memory_total_mb":49140,"temperature":73},{"index":5,"name":"NVIDIA RTX A6000","utilization":70,"memory_used_mb":4761,"memory_total_mb":49140,"temperature":68},{"index":6,"name":"NVIDIA RTX A6000","utilization":0,"memory_used_mb":11390,"memory_total_mb":49140,"temperature":40},{"index":7,"name":"NVIDIA RTX A6000","utilization":6,"memory_used_mb":5921,"memory_total_mb":49140,"temperature":37}],
  "cpu": {"cores": 48, "load_avg": 40.36, "usage_percent": 62.0},
  "memory": {"used_mb": 84618, "total_mb": 709363, "percent": 11.9},
  "disk": {"used": "2.7T", "total": "3.6T", "percent": 80},
  "users": ["ispl"],
  "gpu_processes": [{"pid":2661019,"name":"python","memory_mb":5576},{"pid":2662361,"name":"python","memory_mb":586},{"pid":2592963,"name":"python","memory_mb":20646},{"pid":2617897,"name":"/home/ispl/anaconda3/envs/MSGS/bin/python","memory_mb":12050},{"pid":2619159,"name":"/home/ispl/anaconda3/envs/MSGS/bin/python","memory_mb":11500},{"pid":2542060,"name":"python","memory_mb":4746},{"pid":2658753,"name":"python","memory_mb":9508},{"pid":2661599,"name":"/home/ispl/anaconda3/envs/MSGS/bin/python","memory_mb":2364},{"pid":2656794,"name":"/home/ispl/anaconda3/envs/MSGS/bin/python","memory_mb":5906}]
},
    {
  "name": "CPU1",
  "type": "cpu",
  "status": "online",
  "timestamp": "2026-05-27T17:15:17Z",
  "cpu": {"cores": 64, "load_avg": 0.00, "usage_percent": 0.0},
  "memory": {"used_mb": 4391, "total_mb": 773344, "percent": 0.6},
  "disk": {"used": "35G", "total": "879G", "percent": 5},
  "users": ["user"]
},
    {
  "name": "CPU2",
  "type": "cpu",
  "status": "online",
  "timestamp": "2026-05-27T17:15:17Z",
  "cpu": {"cores": 64, "load_avg": 0.16, "usage_percent": 0.2},
  "memory": {"used_mb": 6811, "total_mb": 773344, "percent": 0.9},
  "disk": {"used": "47G", "total": "879G", "percent": 6},
  "users": ["user"]
},
    {
  "name": "CPU3",
  "type": "cpu",
  "status": "online",
  "timestamp": "2026-05-27T17:15:17Z",
  "cpu": {"cores": 64, "load_avg": 20.18, "usage_percent": 31.4},
  "memory": {"used_mb": 48254, "total_mb": 773344, "percent": 6.2},
  "disk": {"used": "37G", "total": "879G", "percent": 5},
  "users": ["user"]
},
    {
  "name": "CPU4",
  "type": "cpu",
  "status": "online",
  "timestamp": "2026-05-27T17:15:17Z",
  "cpu": {"cores": 64, "load_avg": 16.87, "usage_percent": 26.6},
  "memory": {"used_mb": 69406, "total_mb": 773344, "percent": 9.0},
  "disk": {"used": "167G", "total": "879G", "percent": 20},
  "users": ["user"]
}
  ]
}
