{
  "last_updated": "2026-05-11T12:20:30Z",
  "servers": [
    {
  "name": "NIPA_server",
  "type": "gpu",
  "status": "online",
  "timestamp": "2026-05-11T12:20:30Z",
  "gpu_count": 1,
  "gpu_memory_gb": 80,
  "gpus": [{"index":0,"name":"NVIDIA H100 80GB HBM3","utilization":100,"memory_used_mb":25172,"memory_total_mb":81559,"temperature":45}],
  "cpu": {"cores": 24, "load_avg": 6.38, "usage_percent": 14.1},
  "memory": {"used_mb": 20874, "total_mb": 241600, "percent": 8.6},
  "disk": {"used": "746G", "total": "993G", "percent": 76},
  "users": ["ispl"],
  "gpu_processes": [{"pid":2311343,"name":"python","memory_mb":4700},{"pid":2312752,"name":"/home/ispl/anaconda3/envs/pnm_ugs/bin/DH_3DGM_v00","memory_mb":8778},{"pid":2319806,"name":"python","memory_mb":7764},{"pid":2325541,"name":"python","memory_mb":3906}]
},
    {
  "name": "ISPL",
  "type": "gpu",
  "status": "online",
  "timestamp": "2026-05-11T12:20:30Z",
  "gpu_count": 8,
  "gpu_memory_gb": 48,
  "gpus": [{"index":0,"name":"NVIDIA RTX A6000","utilization":100,"memory_used_mb":46359,"memory_total_mb":49140,"temperature":63},{"index":1,"name":"NVIDIA RTX A6000","utilization":100,"memory_used_mb":48349,"memory_total_mb":49140,"temperature":61},{"index":2,"name":"NVIDIA RTX A6000","utilization":100,"memory_used_mb":48386,"memory_total_mb":49140,"temperature":69},{"index":3,"name":"NVIDIA RTX A6000","utilization":100,"memory_used_mb":44269,"memory_total_mb":49140,"temperature":73},{"index":4,"name":"NVIDIA RTX A6000","utilization":99,"memory_used_mb":19173,"memory_total_mb":49140,"temperature":72},{"index":5,"name":"NVIDIA RTX A6000","utilization":98,"memory_used_mb":48333,"memory_total_mb":49140,"temperature":66},{"index":6,"name":"NVIDIA RTX A6000","utilization":99,"memory_used_mb":19281,"memory_total_mb":49140,"temperature":70},{"index":7,"name":"NVIDIA RTX A6000","utilization":98,"memory_used_mb":29803,"memory_total_mb":49140,"temperature":62}],
  "cpu": {"cores": 48, "load_avg": 26.77, "usage_percent": 6.1},
  "memory": {"used_mb": 195948, "total_mb": 709363, "percent": 27.6},
  "disk": {"used": "2.1T", "total": "3.6T", "percent": 61},
  "users": ["ispl"],
  "gpu_processes": [{"pid":678522,"name":"/home/ispl/anaconda3/envs/dongho-mip-splatting/bin/python","memory_mb":20882},{"pid":678494,"name":"/home/ispl/anaconda3/envs/dongho-mip-splatting/bin/python","memory_mb":12206},{"pid":678766,"name":"/home/ispl/anaconda3/envs/dongho-mip-splatting/bin/python","memory_mb":13250},{"pid":678525,"name":"/home/ispl/anaconda3/envs/dongho-mip-splatting/bin/python","memory_mb":16334},{"pid":678780,"name":"/home/ispl/anaconda3/envs/dongho-mip-splatting/bin/python","memory_mb":24182},{"pid":678590,"name":"/home/ispl/anaconda3/envs/dongho-mip-splatting/bin/python","memory_mb":7812},{"pid":678536,"name":"/home/ispl/anaconda3/envs/dongho-mip-splatting/bin/python","memory_mb":18210},{"pid":678657,"name":"/home/ispl/anaconda3/envs/dongho-mip-splatting/bin/python","memory_mb":5518},{"pid":678519,"name":"/home/ispl/anaconda3/envs/dongho-mip-splatting/bin/python","memory_mb":14692},{"pid":678730,"name":"/home/ispl/anaconda3/envs/dongho-mip-splatting/bin/python","memory_mb":9942},{"pid":678535,"name":"/home/ispl/anaconda3/envs/dongho-mip-splatting/bin/python","memory_mb":11904},{"pid":678506,"name":"/home/ispl/anaconda3/envs/dongho-mip-splatting/bin/python","memory_mb":15848},{"pid":678975,"name":"/home/ispl/anaconda3/envs/dongho-mip-splatting/bin/python","memory_mb":16496},{"pid":1030275,"name":"/home/ispl/anaconda3/envs/dongho-mip-splatting/bin/python","memory_mb":19158},{"pid":1088747,"name":"/home/ispl/anaconda3/envs/dongho-mip-splatting/bin/python","memory_mb":48318},{"pid":969557,"name":"/home/ispl/anaconda3/envs/dongho-mip-splatting/bin/python","memory_mb":19266},{"pid":1082905,"name":"/home/ispl/anaconda3/envs/dongho-mip-splatting/bin/python","memory_mb":29788}]
},
    {
  "name": "CPU1",
  "type": "cpu",
  "status": "online",
  "timestamp": "2026-05-11T12:20:30Z",
  "cpu": {"cores": 64, "load_avg": 0.00, "usage_percent": 0.1},
  "memory": {"used_mb": 4469, "total_mb": 773344, "percent": 0.6},
  "disk": {"used": "35G", "total": "879G", "percent": 5},
  "users": []
},
    {
  "name": "CPU2",
  "type": "cpu",
  "status": "online",
  "timestamp": "2026-05-11T12:20:30Z",
  "cpu": {"cores": 64, "load_avg": 0.15, "usage_percent": 0.2},
  "memory": {"used_mb": 6176, "total_mb": 773344, "percent": 0.8},
  "disk": {"used": "46G", "total": "879G", "percent": 6},
  "users": ["user"]
},
    {
  "name": "CPU3",
  "type": "cpu",
  "status": "online",
  "timestamp": "2026-05-11T12:20:30Z",
  "cpu": {"cores": 64, "load_avg": 0.00, "usage_percent": 0.1},
  "memory": {"used_mb": 3979, "total_mb": 773344, "percent": 0.5},
  "disk": {"used": "33G", "total": "879G", "percent": 4},
  "users": ["user"]
},
    {
  "name": "CPU4",
  "type": "cpu",
  "status": "online",
  "timestamp": "2026-05-11T12:20:30Z",
  "cpu": {"cores": 64, "load_avg": 23.05, "usage_percent": 36.0},
  "memory": {"used_mb": 54937, "total_mb": 773344, "percent": 7.1},
  "disk": {"used": "162G", "total": "879G", "percent": 20},
  "users": ["user"]
}
  ]
}
