{
  "last_updated": "2026-05-02T03:35:47Z",
  "servers": [
    {
  "name": "NIPA_server",
  "type": "gpu",
  "status": "online",
  "timestamp": "2026-05-02T03:35:47Z",
  "gpu_count": 1,
  "gpu_memory_gb": 80,
  "gpus": [{"index":0,"name":"NVIDIA H100 80GB HBM3","utilization":100,"memory_used_mb":25005,"memory_total_mb":81559,"temperature":44}],
  "cpu": {"cores": 24, "load_avg": 2.27, "usage_percent": 9.2},
  "memory": {"used_mb": 22855, "total_mb": 241600, "percent": 9.5},
  "disk": {"used": "643G", "total": "993G", "percent": 65},
  "users": ["ispl"],
  "gpu_processes": [{"pid":1811488,"name":"/home/ispl/anaconda3/envs/pnm_sargs/bin/DH_SARGS_v00","memory_mb":11400},{"pid":1820763,"name":"/home/ispl/anaconda3/envs/pnm_amgs/bin/DH_AMGS_v38","memory_mb":13590}]
},
    {
  "name": "ISPL",
  "type": "gpu",
  "status": "online",
  "timestamp": "2026-05-02T03:35:47Z",
  "gpu_count": 8,
  "gpu_memory_gb": 48,
  "gpus": [{"index":0,"name":"NVIDIA RTX A6000","utilization":97,"memory_used_mb":14725,"memory_total_mb":49140,"temperature":60},{"index":1,"name":"NVIDIA RTX A6000","utilization":0,"memory_used_mb":10657,"memory_total_mb":49140,"temperature":40},{"index":2,"name":"NVIDIA RTX A6000","utilization":0,"memory_used_mb":10,"memory_total_mb":49140,"temperature":26},{"index":3,"name":"NVIDIA RTX A6000","utilization":0,"memory_used_mb":10,"memory_total_mb":49140,"temperature":27},{"index":4,"name":"NVIDIA RTX A6000","utilization":84,"memory_used_mb":7075,"memory_total_mb":49140,"temperature":66},{"index":5,"name":"NVIDIA RTX A6000","utilization":99,"memory_used_mb":20333,"memory_total_mb":49140,"temperature":71},{"index":6,"name":"NVIDIA RTX A6000","utilization":98,"memory_used_mb":9563,"memory_total_mb":49140,"temperature":59},{"index":7,"name":"NVIDIA RTX A6000","utilization":1,"memory_used_mb":1279,"memory_total_mb":49140,"temperature":32}],
  "cpu": {"cores": 48, "load_avg": 18.93, "usage_percent": 3.8},
  "memory": {"used_mb": 65332, "total_mb": 709363, "percent": 9.2},
  "disk": {"used": "1.8T", "total": "3.6T", "percent": 52},
  "users": ["ispl"],
  "gpu_processes": [{"pid":2657721,"name":"python","memory_mb":14710},{"pid":2657545,"name":"python","memory_mb":12532},{"pid":2652380,"name":"python","memory_mb":7060},{"pid":2572930,"name":"python","memory_mb":20318},{"pid":2685962,"name":"python","memory_mb":9378},{"pid":2695256,"name":"python","memory_mb":1664}]
},
    {
  "name": "CPU1",
  "type": "cpu",
  "status": "online",
  "timestamp": "2026-05-02T03:35:47Z",
  "cpu": {"cores": 64, "load_avg": 0.08, "usage_percent": 0.0},
  "memory": {"used_mb": 4326, "total_mb": 773344, "percent": 0.6},
  "disk": {"used": "35G", "total": "879G", "percent": 5},
  "users": []
},
    {
  "name": "CPU2",
  "type": "cpu",
  "status": "online",
  "timestamp": "2026-05-02T03:35:47Z",
  "cpu": {"cores": 64, "load_avg": 0.02, "usage_percent": 0.2},
  "memory": {"used_mb": 6146, "total_mb": 773344, "percent": 0.8},
  "disk": {"used": "46G", "total": "879G", "percent": 6},
  "users": ["user"]
},
    {
  "name": "CPU3",
  "type": "cpu",
  "status": "online",
  "timestamp": "2026-05-02T03:35:47Z",
  "cpu": {"cores": 64, "load_avg": 0.12, "usage_percent": 0.1},
  "memory": {"used_mb": 3934, "total_mb": 773344, "percent": 0.5},
  "disk": {"used": "33G", "total": "879G", "percent": 4},
  "users": ["user"]
},
    {
  "name": "CPU4",
  "type": "cpu",
  "status": "online",
  "timestamp": "2026-05-02T03:35:47Z",
  "cpu": {"cores": 64, "load_avg": 25.07, "usage_percent": 37.7},
  "memory": {"used_mb": 48431, "total_mb": 773344, "percent": 6.3},
  "disk": {"used": "159G", "total": "879G", "percent": 20},
  "users": ["user"]
}
  ]
}
