{
  "last_updated": "2026-05-26T16:05:12Z",
  "servers": [
    {
  "name": "NIPA_server",
  "type": "gpu",
  "status": "online",
  "timestamp": "2026-05-26T16:05:12Z",
  "gpu_count": 1,
  "gpu_memory_gb": 80,
  "gpus": [{"index":0,"name":"NVIDIA H100 80GB HBM3","utilization":100,"memory_used_mb":45315,"memory_total_mb":81559,"temperature":42}],
  "cpu": {"cores": 24, "load_avg": 9.33, "usage_percent": 32.2},
  "memory": {"used_mb": 72003, "total_mb": 241600, "percent": 29.8},
  "disk": {"used": "919G", "total": "993G", "percent": 93},
  "users": ["ispl"],
  "gpu_processes": [{"pid":849487,"name":"python","memory_mb":4178},{"pid":851080,"name":"python","memory_mb":3506},{"pid":853673,"name":"python","memory_mb":5434},{"pid":1153872,"name":"python","memory_mb":3012},{"pid":1548923,"name":"APGS_ellipsoid","memory_mb":11966},{"pid":1714493,"name":"/home/ispl/anaconda3/envs/hac_plus/bin/APGS_voxel","memory_mb":6712},{"pid":1773652,"name":"python","memory_mb":10462}]
},
    {
  "name": "ISPL",
  "type": "gpu",
  "status": "online",
  "timestamp": "2026-05-26T16:05:12Z",
  "gpu_count": 8,
  "gpu_memory_gb": 48,
  "gpus": [{"index":0,"name":"NVIDIA RTX A6000","utilization":0,"memory_used_mb":8391,"memory_total_mb":49140,"temperature":47},{"index":1,"name":"NVIDIA RTX A6000","utilization":98,"memory_used_mb":15067,"memory_total_mb":49140,"temperature":56},{"index":2,"name":"NVIDIA RTX A6000","utilization":0,"memory_used_mb":40183,"memory_total_mb":49140,"temperature":41},{"index":3,"name":"NVIDIA RTX A6000","utilization":0,"memory_used_mb":10,"memory_total_mb":49140,"temperature":30},{"index":4,"name":"NVIDIA RTX A6000","utilization":99,"memory_used_mb":12247,"memory_total_mb":49140,"temperature":77},{"index":5,"name":"NVIDIA RTX A6000","utilization":100,"memory_used_mb":10797,"memory_total_mb":49140,"temperature":74},{"index":6,"name":"NVIDIA RTX A6000","utilization":96,"memory_used_mb":10001,"memory_total_mb":49140,"temperature":66},{"index":7,"name":"NVIDIA RTX A6000","utilization":0,"memory_used_mb":13441,"memory_total_mb":49140,"temperature":62}],
  "cpu": {"cores": 48, "load_avg": 17.49, "usage_percent": 7.2},
  "memory": {"used_mb": 70187, "total_mb": 709363, "percent": 9.9},
  "disk": {"used": "3.0T", "total": "3.6T", "percent": 88},
  "users": ["ispl"],
  "gpu_processes": [{"pid":3607384,"name":"python","memory_mb":6964},{"pid":3492395,"name":"python","memory_mb":17374},{"pid":3555632,"name":"python","memory_mb":40168},{"pid":3576843,"name":"python","memory_mb":12232},{"pid":3601044,"name":"python","memory_mb":10782},{"pid":3623941,"name":"python","memory_mb":9656},{"pid":3608051,"name":"python","memory_mb":13432}]
},
    {
  "name": "CPU1",
  "type": "cpu",
  "status": "online",
  "timestamp": "2026-05-26T16:05:12Z",
  "cpu": {"cores": 64, "load_avg": 0.06, "usage_percent": 0.1},
  "memory": {"used_mb": 4410, "total_mb": 773344, "percent": 0.6},
  "disk": {"used": "35G", "total": "879G", "percent": 5},
  "users": ["user"]
},
    {
  "name": "CPU2",
  "type": "cpu",
  "status": "online",
  "timestamp": "2026-05-26T16:05:12Z",
  "cpu": {"cores": 64, "load_avg": 0.18, "usage_percent": 0.2},
  "memory": {"used_mb": 6816, "total_mb": 773344, "percent": 0.9},
  "disk": {"used": "47G", "total": "879G", "percent": 6},
  "users": ["user"]
},
    {
  "name": "CPU3",
  "type": "cpu",
  "status": "online",
  "timestamp": "2026-05-26T16:05:12Z",
  "cpu": {"cores": 64, "load_avg": 12.13, "usage_percent": 18.9},
  "memory": {"used_mb": 64970, "total_mb": 773344, "percent": 8.4},
  "disk": {"used": "37G", "total": "879G", "percent": 5},
  "users": ["user"]
},
    {
  "name": "CPU4",
  "type": "cpu",
  "status": "online",
  "timestamp": "2026-05-26T16:05:12Z",
  "cpu": {"cores": 64, "load_avg": 14.11, "usage_percent": 21.9},
  "memory": {"used_mb": 84833, "total_mb": 773344, "percent": 11.0},
  "disk": {"used": "167G", "total": "879G", "percent": 20},
  "users": ["user"]
}
  ]
}
