{
  "last_updated": "2026-06-09T02:29:54Z",
  "servers": [
    {
  "name": "NIPA_server",
  "type": "gpu",
  "status": "online",
  "timestamp": "2026-06-09T02:29:54Z",
  "gpu_count": 1,
  "gpu_memory_gb": 80,
  "gpus": [{"index":0,"name":"NVIDIA H100 80GB HBM3","utilization":95,"memory_used_mb":18653,"memory_total_mb":81559,"temperature":45}],
  "cpu": {"cores": 24, "load_avg": 25.99, "usage_percent": 93.2},
  "memory": {"used_mb": 17461, "total_mb": 241600, "percent": 7.2},
  "disk": {"used": "942G", "total": "993G", "percent": 95},
  "users": ["ispl"],
  "gpu_processes": [{"pid":3728347,"name":"/home/ispl/anaconda3/envs/hac_plus/bin/APGS_voxel","memory_mb":16034},{"pid":30979,"name":"python","memory_mb":2604}]
},
    {
  "name": "ISPL",
  "type": "gpu",
  "status": "online",
  "timestamp": "2026-06-09T02:29:54Z",
  "gpu_count": 8,
  "gpu_memory_gb": 48,
  "gpus": [{"index":0,"name":"NVIDIA RTX A6000","utilization":99,"memory_used_mb":15101,"memory_total_mb":49140,"temperature":68},{"index":1,"name":"NVIDIA RTX A6000","utilization":92,"memory_used_mb":4001,"memory_total_mb":49140,"temperature":49},{"index":2,"name":"NVIDIA RTX A6000","utilization":0,"memory_used_mb":1457,"memory_total_mb":49140,"temperature":52},{"index":3,"name":"NVIDIA RTX A6000","utilization":0,"memory_used_mb":7689,"memory_total_mb":49140,"temperature":47},{"index":4,"name":"NVIDIA RTX A6000","utilization":99,"memory_used_mb":13215,"memory_total_mb":49140,"temperature":69},{"index":5,"name":"NVIDIA RTX A6000","utilization":83,"memory_used_mb":6393,"memory_total_mb":49140,"temperature":75},{"index":6,"name":"NVIDIA RTX A6000","utilization":0,"memory_used_mb":39297,"memory_total_mb":49140,"temperature":49},{"index":7,"name":"NVIDIA RTX A6000","utilization":52,"memory_used_mb":14931,"memory_total_mb":49140,"temperature":67}],
  "cpu": {"cores": 48, "load_avg": 57.34, "usage_percent": 20.3},
  "memory": {"used_mb": 102670, "total_mb": 709363, "percent": 14.5},
  "disk": {"used": "2.7T", "total": "3.6T", "percent": 78},
  "users": ["ispl"],
  "gpu_processes": [{"pid":1074894,"name":"python","memory_mb":15086},{"pid":1258578,"name":"/home/ispl/anaconda3/envs/dongho-mip-splatting/bin/python","memory_mb":3996},{"pid":1260501,"name":"python","memory_mb":2276},{"pid":1258581,"name":"/home/ispl/anaconda3/envs/dongho-mip-splatting/bin/python","memory_mb":7690},{"pid":1192458,"name":"python","memory_mb":13200},{"pid":1086759,"name":"python","memory_mb":6474},{"pid":1198603,"name":"python","memory_mb":39282},{"pid":1236458,"name":"/home/ispl/anaconda3/envs/dongho-mip-splatting/bin/python","memory_mb":16464}]
},
    {
  "name": "CPU1",
  "type": "cpu",
  "status": "online",
  "timestamp": "2026-06-09T02:29:54Z",
  "cpu": {"cores": 64, "load_avg": 0.03, "usage_percent": 0.0},
  "memory": {"used_mb": 4466, "total_mb": 773344, "percent": 0.6},
  "disk": {"used": "36G", "total": "879G", "percent": 5},
  "users": ["user"]
},
    {
  "name": "CPU2",
  "type": "cpu",
  "status": "online",
  "timestamp": "2026-06-09T02:29:54Z",
  "cpu": {"cores": 64, "load_avg": 0.20, "usage_percent": 0.2},
  "memory": {"used_mb": 6983, "total_mb": 773344, "percent": 0.9},
  "disk": {"used": "46G", "total": "879G", "percent": 6},
  "users": ["user"]
},
    {
  "name": "CPU3",
  "type": "cpu",
  "status": "online",
  "timestamp": "2026-06-09T02:29:54Z",
  "cpu": {"cores": 64, "load_avg": 11.22, "usage_percent": 17.3},
  "memory": {"used_mb": 18481, "total_mb": 773344, "percent": 2.4},
  "disk": {"used": "38G", "total": "879G", "percent": 5},
  "users": ["user"]
},
    {
  "name": "CPU4",
  "type": "cpu",
  "status": "online",
  "timestamp": "2026-06-09T02:29:54Z",
  "cpu": {"cores": 64, "load_avg": 7.13, "usage_percent": 11.0},
  "memory": {"used_mb": 21250, "total_mb": 773344, "percent": 2.7},
  "disk": {"used": "162G", "total": "879G", "percent": 20},
  "users": ["user"]
}
  ]
}
