{
  "last_updated": "2026-05-03T18:21:50Z",
  "servers": [
    {
  "name": "NIPA_server",
  "type": "gpu",
  "status": "online",
  "timestamp": "2026-05-03T18:21:50Z",
  "gpu_count": 1,
  "gpu_memory_gb": 80,
  "gpus": [{"index":0,"name":"NVIDIA H100 80GB HBM3","utilization":100,"memory_used_mb":52298,"memory_total_mb":81559,"temperature":48}],
  "cpu": {"cores": 24, "load_avg": 4.54, "usage_percent": 17.8},
  "memory": {"used_mb": 28829, "total_mb": 241600, "percent": 11.9},
  "disk": {"used": "702G", "total": "993G", "percent": 71},
  "users": ["ispl"],
  "gpu_processes": [{"pid":3338494,"name":"/home/ispl/anaconda3/envs/pnm_sargs/bin/DH_SARGS_v00","memory_mb":12268},{"pid":3338497,"name":"/home/ispl/anaconda3/envs/pnm_sargs/bin/DH_SARGS_v00","memory_mb":13644},{"pid":3338495,"name":"/home/ispl/anaconda3/envs/pnm_sargs/bin/DH_SARGS_v00","memory_mb":13214},{"pid":3338496,"name":"/home/ispl/anaconda3/envs/pnm_sargs/bin/DH_SARGS_v00","memory_mb":13146}]
},
    {
  "name": "ISPL",
  "type": "gpu",
  "status": "online",
  "timestamp": "2026-05-03T18:21:50Z",
  "gpu_count": 8,
  "gpu_memory_gb": 48,
  "gpus": [{"index":0,"name":"NVIDIA RTX A6000","utilization":0,"memory_used_mb":10,"memory_total_mb":49140,"temperature":26},{"index":1,"name":"NVIDIA RTX A6000","utilization":10,"memory_used_mb":12763,"memory_total_mb":49140,"temperature":32},{"index":2,"name":"NVIDIA RTX A6000","utilization":98,"memory_used_mb":11381,"memory_total_mb":49140,"temperature":73},{"index":3,"name":"NVIDIA RTX A6000","utilization":97,"memory_used_mb":11513,"memory_total_mb":49140,"temperature":73},{"index":4,"name":"NVIDIA RTX A6000","utilization":100,"memory_used_mb":18391,"memory_total_mb":49140,"temperature":73},{"index":5,"name":"NVIDIA RTX A6000","utilization":99,"memory_used_mb":18075,"memory_total_mb":49140,"temperature":74},{"index":6,"name":"NVIDIA RTX A6000","utilization":100,"memory_used_mb":15011,"memory_total_mb":49140,"temperature":70},{"index":7,"name":"NVIDIA RTX A6000","utilization":97,"memory_used_mb":15421,"memory_total_mb":49140,"temperature":60}],
  "cpu": {"cores": 48, "load_avg": 17.68, "usage_percent": 4.4},
  "memory": {"used_mb": 89088, "total_mb": 709363, "percent": 12.6},
  "disk": {"used": "1.8T", "total": "3.6T", "percent": 53},
  "users": ["ispl"],
  "gpu_processes": [{"pid":3003523,"name":"/home/ispl/anaconda3/envs/MSGS/bin/python","memory_mb":12748},{"pid":2951830,"name":"/home/ispl/anaconda3/envs/MSGS/bin/python","memory_mb":11366},{"pid":2953267,"name":"/home/ispl/anaconda3/envs/MSGS/bin/python","memory_mb":11498},{"pid":2831068,"name":"/home/ispl/anaconda3/envs/dongho-mip-splatting/bin/python","memory_mb":18376},{"pid":2831073,"name":"/home/ispl/anaconda3/envs/dongho-mip-splatting/bin/python","memory_mb":18060},{"pid":2831072,"name":"/home/ispl/anaconda3/envs/dongho-aaa-gs/bin/python","memory_mb":14996},{"pid":2831071,"name":"/home/ispl/anaconda3/envs/dongho-aaa-gs/bin/python","memory_mb":15406}]
},
    {
  "name": "CPU1",
  "type": "cpu",
  "status": "online",
  "timestamp": "2026-05-03T18:21:50Z",
  "cpu": {"cores": 64, "load_avg": 0.01, "usage_percent": 0.1},
  "memory": {"used_mb": 4368, "total_mb": 773344, "percent": 0.6},
  "disk": {"used": "34G", "total": "879G", "percent": 5},
  "users": []
},
    {
  "name": "CPU2",
  "type": "cpu",
  "status": "online",
  "timestamp": "2026-05-03T18:21:50Z",
  "cpu": {"cores": 64, "load_avg": 0.11, "usage_percent": 0.2},
  "memory": {"used_mb": 6113, "total_mb": 773344, "percent": 0.8},
  "disk": {"used": "46G", "total": "879G", "percent": 6},
  "users": ["user"]
},
    {
  "name": "CPU3",
  "type": "cpu",
  "status": "online",
  "timestamp": "2026-05-03T18:21:50Z",
  "cpu": {"cores": 64, "load_avg": 0.04, "usage_percent": 0.0},
  "memory": {"used_mb": 3976, "total_mb": 773344, "percent": 0.5},
  "disk": {"used": "33G", "total": "879G", "percent": 4},
  "users": ["user"]
},
    {
  "name": "CPU4",
  "type": "cpu",
  "status": "online",
  "timestamp": "2026-05-03T18:21:50Z",
  "cpu": {"cores": 64, "load_avg": 33.23, "usage_percent": 51.7},
  "memory": {"used_mb": 74275, "total_mb": 773344, "percent": 9.6},
  "disk": {"used": "159G", "total": "879G", "percent": 20},
  "users": ["user"]
}
  ]
}
