{
  "last_updated": "2026-06-08T04:57:36Z",
  "servers": [
    {
  "name": "NIPA_server",
  "type": "gpu",
  "status": "online",
  "timestamp": "2026-06-08T04:57:36Z",
  "gpu_count": 1,
  "gpu_memory_gb": 80,
  "gpus": [{"index":0,"name":"NVIDIA H100 80GB HBM3","utilization":100,"memory_used_mb":28778,"memory_total_mb":81559,"temperature":42}],
  "cpu": {"cores": 24, "load_avg": 5.61, "usage_percent": 37.1},
  "memory": {"used_mb": 28343, "total_mb": 241600, "percent": 11.7},
  "disk": {"used": "927G", "total": "993G", "percent": 94},
  "users": ["ispl"],
  "gpu_processes": [{"pid":2359713,"name":"/home/ispl/anaconda3/envs/hac_plus/bin/APGS_voxel","memory_mb":16162},{"pid":2621323,"name":"python","memory_mb":3844},{"pid":2631739,"name":"python","memory_mb":6450},{"pid":2632182,"name":"python","memory_mb":2296}]
},
    {
  "name": "ISPL",
  "type": "gpu",
  "status": "online",
  "timestamp": "2026-06-08T04:57:36Z",
  "gpu_count": 8,
  "gpu_memory_gb": 48,
  "gpus": [{"index":0,"name":"NVIDIA RTX A6000","utilization":0,"memory_used_mb":11255,"memory_total_mb":49140,"temperature":63},{"index":1,"name":"NVIDIA RTX A6000","utilization":100,"memory_used_mb":20015,"memory_total_mb":49140,"temperature":66},{"index":2,"name":"NVIDIA RTX A6000","utilization":99,"memory_used_mb":14553,"memory_total_mb":49140,"temperature":77},{"index":3,"name":"NVIDIA RTX A6000","utilization":99,"memory_used_mb":21507,"memory_total_mb":49140,"temperature":76},{"index":4,"name":"NVIDIA RTX A6000","utilization":87,"memory_used_mb":11937,"memory_total_mb":49140,"temperature":83},{"index":5,"name":"NVIDIA RTX A6000","utilization":100,"memory_used_mb":17357,"memory_total_mb":49140,"temperature":75},{"index":6,"name":"NVIDIA RTX A6000","utilization":72,"memory_used_mb":43532,"memory_total_mb":49140,"temperature":65},{"index":7,"name":"NVIDIA RTX A6000","utilization":99,"memory_used_mb":14433,"memory_total_mb":49140,"temperature":68}],
  "cpu": {"cores": 48, "load_avg": 22.56, "usage_percent": 8.0},
  "memory": {"used_mb": 114659, "total_mb": 709363, "percent": 16.2},
  "disk": {"used": "2.6T", "total": "3.6T", "percent": 76},
  "users": ["ispl"],
  "gpu_processes": [{"pid":2174955,"name":"python","memory_mb":13116},{"pid":1891252,"name":"python","memory_mb":20000},{"pid":2199406,"name":"python","memory_mb":14316},{"pid":1901645,"name":"python","memory_mb":21492},{"pid":2096399,"name":"python","memory_mb":5296},{"pid":2183523,"name":"python","memory_mb":17324},{"pid":2132690,"name":"python","memory_mb":3602},{"pid":2243620,"name":"python","memory_mb":39912},{"pid":2085465,"name":"python","memory_mb":14418}]
},
    {
  "name": "CPU1",
  "type": "cpu",
  "status": "online",
  "timestamp": "2026-06-08T04:57:36Z",
  "cpu": {"cores": 64, "load_avg": 0.08, "usage_percent": 0.0},
  "memory": {"used_mb": 4538, "total_mb": 773344, "percent": 0.6},
  "disk": {"used": "36G", "total": "879G", "percent": 5},
  "users": ["user"]
},
    {
  "name": "CPU2",
  "type": "cpu",
  "status": "online",
  "timestamp": "2026-06-08T04:57:36Z",
  "cpu": {"cores": 64, "load_avg": 0.06, "usage_percent": 0.2},
  "memory": {"used_mb": 6936, "total_mb": 773344, "percent": 0.9},
  "disk": {"used": "46G", "total": "879G", "percent": 6},
  "users": ["user"]
},
    {
  "name": "CPU3",
  "type": "cpu",
  "status": "online",
  "timestamp": "2026-06-08T04:57:36Z",
  "cpu": {"cores": 64, "load_avg": 11.09, "usage_percent": 17.3},
  "memory": {"used_mb": 13291, "total_mb": 773344, "percent": 1.7},
  "disk": {"used": "38G", "total": "879G", "percent": 5},
  "users": ["user"]
},
    {
  "name": "CPU4",
  "type": "cpu",
  "status": "online",
  "timestamp": "2026-06-08T04:57:36Z",
  "cpu": {"cores": 64, "load_avg": 14.10, "usage_percent": 21.9},
  "memory": {"used_mb": 36919, "total_mb": 773344, "percent": 4.8},
  "disk": {"used": "162G", "total": "879G", "percent": 20},
  "users": ["user"]
}
  ]
}
