{
  "last_updated": "2026-06-13T17:17:13Z",
  "servers": [
    {
  "name": "NIPA_server",
  "type": "gpu",
  "status": "online",
  "timestamp": "2026-06-13T17:17:13Z",
  "gpu_count": 1,
  "gpu_memory_gb": 80,
  "gpus": [{"index":0,"name":"NVIDIA H100 80GB HBM3","utilization":37,"memory_used_mb":8089,"memory_total_mb":81559,"temperature":39}],
  "cpu": {"cores": 24, "load_avg": 2.19, "usage_percent": 6.1},
  "memory": {"used_mb": 11896, "total_mb": 241600, "percent": 4.9},
  "disk": {"used": "955G", "total": "993G", "percent": 97},
  "users": ["ispl"],
  "gpu_processes": [{"pid":3409308,"name":"/home/ispl/anaconda3/envs/hac_plus/bin/python","memory_mb":8080}]
},
    {
  "name": "ISPL",
  "type": "gpu",
  "status": "online",
  "timestamp": "2026-06-13T17:17:13Z",
  "gpu_count": 8,
  "gpu_memory_gb": 48,
  "gpus": [{"index":0,"name":"NVIDIA RTX A6000","utilization":85,"memory_used_mb":5059,"memory_total_mb":49140,"temperature":52},{"index":1,"name":"NVIDIA RTX A6000","utilization":0,"memory_used_mb":5539,"memory_total_mb":49140,"temperature":32},{"index":2,"name":"NVIDIA RTX A6000","utilization":85,"memory_used_mb":9095,"memory_total_mb":49140,"temperature":68},{"index":3,"name":"NVIDIA RTX A6000","utilization":99,"memory_used_mb":21521,"memory_total_mb":49140,"temperature":64},{"index":4,"name":"NVIDIA RTX A6000","utilization":84,"memory_used_mb":13201,"memory_total_mb":49140,"temperature":70},{"index":5,"name":"NVIDIA RTX A6000","utilization":0,"memory_used_mb":607,"memory_total_mb":49140,"temperature":36},{"index":6,"name":"NVIDIA RTX A6000","utilization":92,"memory_used_mb":13195,"memory_total_mb":49140,"temperature":69},{"index":7,"name":"NVIDIA RTX A6000","utilization":86,"memory_used_mb":9231,"memory_total_mb":49140,"temperature":61}],
  "cpu": {"cores": 48, "load_avg": 36.64, "usage_percent": 5.4},
  "memory": {"used_mb": 84903, "total_mb": 709363, "percent": 12.0},
  "disk": {"used": "2.9T", "total": "3.6T", "percent": 85},
  "users": ["ispl"],
  "gpu_processes": [{"pid":3936896,"name":"/home/ispl/anaconda3/envs/MSGS/bin/python","memory_mb":5352},{"pid":3928020,"name":"/home/ispl/anaconda3/envs/MSGS/bin/python","memory_mb":5524},{"pid":3911785,"name":"/home/ispl/anaconda3/envs/MSGS/bin/python","memory_mb":9702},{"pid":3716067,"name":"python","memory_mb":21506},{"pid":3782316,"name":"python","memory_mb":13186},{"pid":3944569,"name":"/home/ispl/anaconda3/envs/MSGS/bin/python","memory_mb":664},{"pid":3868625,"name":"/home/ispl/anaconda3/envs/MSGS/bin/python","memory_mb":13180},{"pid":3867450,"name":"/home/ispl/anaconda3/envs/MSGS/bin/python","memory_mb":9216}]
},
    {
  "name": "CPU1",
  "type": "cpu",
  "status": "online",
  "timestamp": "2026-06-13T17:17:13Z",
  "cpu": {"cores": 64, "load_avg": 0.00, "usage_percent": 0.0},
  "memory": {"used_mb": 4518, "total_mb": 773344, "percent": 0.6},
  "disk": {"used": "37G", "total": "879G", "percent": 5},
  "users": ["user"]
},
    {
  "name": "CPU2",
  "type": "cpu",
  "status": "online",
  "timestamp": "2026-06-13T17:17:13Z",
  "cpu": {"cores": 64, "load_avg": 0.18, "usage_percent": 0.2},
  "memory": {"used_mb": 6934, "total_mb": 773344, "percent": 0.9},
  "disk": {"used": "45G", "total": "879G", "percent": 6},
  "users": ["user"]
},
    {
  "name": "CPU3",
  "type": "cpu",
  "status": "online",
  "timestamp": "2026-06-13T17:17:13Z",
  "cpu": {"cores": 64, "load_avg": 0.01, "usage_percent": 0.0},
  "memory": {"used_mb": 5400, "total_mb": 773344, "percent": 0.7},
  "disk": {"used": "39G", "total": "879G", "percent": 5},
  "users": ["user"]
},
    {
  "name": "CPU4",
  "type": "cpu",
  "status": "online",
  "timestamp": "2026-06-13T17:17:13Z",
  "cpu": {"cores": 64, "load_avg": 64.29, "usage_percent": 99.8},
  "memory": {"used_mb": 407492, "total_mb": 773344, "percent": 52.7},
  "disk": {"used": "163G", "total": "879G", "percent": 20},
  "users": ["user"]
}
  ]
}
