{
  "last_updated": "2026-05-20T15:54:06Z",
  "servers": [
    {
  "name": "NIPA_server",
  "type": "gpu",
  "status": "online",
  "timestamp": "2026-05-20T15:54:06Z",
  "gpu_count": 1,
  "gpu_memory_gb": 80,
  "gpus": [{"index":0,"name":"NVIDIA H100 80GB HBM3","utilization":100,"memory_used_mb":23911,"memory_total_mb":81559,"temperature":42}],
  "cpu": {"cores": 24, "load_avg": 5.99, "usage_percent": 17.1},
  "memory": {"used_mb": 20856, "total_mb": 241600, "percent": 8.6},
  "disk": {"used": "834G", "total": "993G", "percent": 84},
  "users": ["ispl"],
  "gpu_processes": [{"pid":783519,"name":"/home/ispl/anaconda3/envs/scaffold_gs/bin/DH_APGS_v15T4G4_drj_s0_t6p0","memory_mb":9982},{"pid":799610,"name":"/home/ispl/anaconda3/envs/hyrf_paperrepro/bin/python","memory_mb":8460},{"pid":845323,"name":"DH_CRGS_v04","memory_mb":6924}]
},
    {
  "name": "ISPL",
  "type": "gpu",
  "status": "online",
  "timestamp": "2026-05-20T15:54:06Z",
  "gpu_count": 8,
  "gpu_memory_gb": 48,
  "gpus": [{"index":0,"name":"NVIDIA RTX A6000","utilization":99,"memory_used_mb":32758,"memory_total_mb":49140,"temperature":69},{"index":1,"name":"NVIDIA RTX A6000","utilization":100,"memory_used_mb":20278,"memory_total_mb":49140,"temperature":62},{"index":2,"name":"NVIDIA RTX A6000","utilization":98,"memory_used_mb":24264,"memory_total_mb":49140,"temperature":65},{"index":3,"name":"NVIDIA RTX A6000","utilization":98,"memory_used_mb":16980,"memory_total_mb":49140,"temperature":60},{"index":4,"name":"NVIDIA RTX A6000","utilization":0,"memory_used_mb":44892,"memory_total_mb":49140,"temperature":36},{"index":5,"name":"NVIDIA RTX A6000","utilization":0,"memory_used_mb":5597,"memory_total_mb":49140,"temperature":36},{"index":6,"name":"NVIDIA RTX A6000","utilization":0,"memory_used_mb":16664,"memory_total_mb":49140,"temperature":61},{"index":7,"name":"NVIDIA RTX A6000","utilization":0,"memory_used_mb":4831,"memory_total_mb":49140,"temperature":33}],
  "cpu": {"cores": 48, "load_avg": 24.00, "usage_percent": 5.2},
  "memory": {"used_mb": 157459, "total_mb": 709363, "percent": 22.2},
  "disk": {"used": "2.1T", "total": "3.6T", "percent": 61},
  "users": ["ispl"],
  "gpu_processes": [{"pid":938024,"name":"python","memory_mb":28288},{"pid":1116993,"name":"/home/ispl/anaconda3/envs/amgs_clean/bin/YH_AMGS_v43abl","memory_mb":4522},{"pid":1037514,"name":"python","memory_mb":15794},{"pid":1117008,"name":"/home/ispl/anaconda3/envs/amgs_clean/bin/YH_AMGS_v43abl","memory_mb":4536},{"pid":1051473,"name":"python","memory_mb":12266},{"pid":1117017,"name":"/home/ispl/anaconda3/envs/amgs_clean/bin/YH_AMGS_v43abl","memory_mb":4566},{"pid":1107957,"name":"python","memory_mb":7858},{"pid":1117025,"name":"/home/ispl/anaconda3/envs/amgs_clean/bin/YH_AMGS_v43abl","memory_mb":4724},{"pid":1062136,"name":"python","memory_mb":40006},{"pid":1117001,"name":"/home/ispl/anaconda3/envs/amgs_clean/bin/YH_AMGS_v43abl","memory_mb":4958},{"pid":1121590,"name":"/home/ispl/anaconda3/envs/amgs_clean/bin/python","memory_mb":6142},{"pid":976292,"name":"python","memory_mb":12132},{"pid":1117033,"name":"/home/ispl/anaconda3/envs/amgs_clean/bin/YH_AMGS_v43abl","memory_mb":4532},{"pid":1117038,"name":"/home/ispl/anaconda3/envs/amgs_clean/bin/YH_AMGS_v43abl","memory_mb":4868}]
},
    {
  "name": "CPU1",
  "type": "cpu",
  "status": "online",
  "timestamp": "2026-05-20T15:54:06Z",
  "cpu": {"cores": 64, "load_avg": 0.00, "usage_percent": 0.1},
  "memory": {"used_mb": 4470, "total_mb": 773344, "percent": 0.6},
  "disk": {"used": "35G", "total": "879G", "percent": 5},
  "users": ["user"]
},
    {
  "name": "CPU2",
  "type": "cpu",
  "status": "online",
  "timestamp": "2026-05-20T15:54:06Z",
  "cpu": {"cores": 64, "load_avg": 0.17, "usage_percent": 0.1},
  "memory": {"used_mb": 6828, "total_mb": 773344, "percent": 0.9},
  "disk": {"used": "47G", "total": "879G", "percent": 6},
  "users": ["user"]
},
    {
  "name": "CPU3",
  "type": "cpu",
  "status": "online",
  "timestamp": "2026-05-20T15:54:06Z",
  "cpu": {"cores": 64, "load_avg": 16.23, "usage_percent": 25.0},
  "memory": {"used_mb": 101911, "total_mb": 773344, "percent": 13.2},
  "disk": {"used": "36G", "total": "879G", "percent": 5},
  "users": ["user"]
},
    {
  "name": "CPU4",
  "type": "cpu",
  "status": "online",
  "timestamp": "2026-05-20T15:54:06Z",
  "cpu": {"cores": 64, "load_avg": 48.21, "usage_percent": 75.1},
  "memory": {"used_mb": 231026, "total_mb": 773344, "percent": 29.9},
  "disk": {"used": "164G", "total": "879G", "percent": 20},
  "users": ["user"]
}
  ]
}
