{
  "last_updated": "2026-06-17T07:48:32Z",
  "servers": [
    {
  "name": "NIPA_server",
  "type": "gpu",
  "status": "online",
  "timestamp": "2026-06-17T07:48:32Z",
  "gpu_count": 1,
  "gpu_memory_gb": 80,
  "gpus": [{"index":0,"name":"NVIDIA H100 80GB HBM3","utilization":100,"memory_used_mb":72400,"memory_total_mb":81559,"temperature":66}],
  "cpu": {"cores": 24, "load_avg": 4.58, "usage_percent": 8.8},
  "memory": {"used_mb": 12710, "total_mb": 241600, "percent": 5.3},
  "disk": {"used": "889G", "total": "993G", "percent": 90},
  "users": ["ispl"],
  "gpu_processes": [{"pid":1800552,"name":"/home/ispl/anaconda3/envs/gs_hb_orig/bin/python","memory_mb":28668},{"pid":1800551,"name":"/home/ispl/anaconda3/envs/gs_hb_orig/bin/python","memory_mb":28668},{"pid":1800553,"name":"/home/ispl/anaconda3/envs/gs_hb_orig/bin/python","memory_mb":15044}]
},
    {
  "name": "ISPL",
  "type": "gpu",
  "status": "online",
  "timestamp": "2026-06-17T07:48:32Z",
  "gpu_count": 8,
  "gpu_memory_gb": 48,
  "gpus": [{"index":0,"name":"NVIDIA RTX A6000","utilization":2,"memory_used_mb":2087,"memory_total_mb":49140,"temperature":37},{"index":1,"name":"NVIDIA RTX A6000","utilization":0,"memory_used_mb":3349,"memory_total_mb":49140,"temperature":35},{"index":2,"name":"NVIDIA RTX A6000","utilization":0,"memory_used_mb":5767,"memory_total_mb":49140,"temperature":40},{"index":3,"name":"NVIDIA RTX A6000","utilization":0,"memory_used_mb":11409,"memory_total_mb":49140,"temperature":39},{"index":4,"name":"NVIDIA RTX A6000","utilization":60,"memory_used_mb":10113,"memory_total_mb":49140,"temperature":54},{"index":5,"name":"NVIDIA RTX A6000","utilization":44,"memory_used_mb":41034,"memory_total_mb":49140,"temperature":55},{"index":6,"name":"NVIDIA RTX A6000","utilization":0,"memory_used_mb":39297,"memory_total_mb":49140,"temperature":38},{"index":7,"name":"NVIDIA RTX A6000","utilization":10,"memory_used_mb":2351,"memory_total_mb":49140,"temperature":37}],
  "cpu": {"cores": 48, "load_avg": 77.16, "usage_percent": 85.1},
  "memory": {"used_mb": 111722, "total_mb": 709363, "percent": 15.7},
  "disk": {"used": "3.1T", "total": "3.6T", "percent": 90},
  "users": ["ispl"],
  "gpu_processes": [{"pid":964178,"name":"python","memory_mb":2072},{"pid":3902606,"name":"python","memory_mb":1914},{"pid":3879406,"name":"python","memory_mb":8212},{"pid":3240360,"name":"python","memory_mb":11394},{"pid":3119193,"name":"/home/ispl/anaconda3/envs/semangs/bin/python","memory_mb":12130},{"pid":3204317,"name":"python","memory_mb":39912},{"pid":3243817,"name":"python","memory_mb":1082},{"pid":3220819,"name":"python","memory_mb":39282},{"pid":2544393,"name":"python","memory_mb":2336}]
},
    {
  "name": "CPU1",
  "type": "cpu",
  "status": "online",
  "timestamp": "2026-06-17T07:48:32Z",
  "cpu": {"cores": 64, "load_avg": 0.03, "usage_percent": 0.0},
  "memory": {"used_mb": 4481, "total_mb": 773344, "percent": 0.6},
  "disk": {"used": "37G", "total": "879G", "percent": 5},
  "users": ["user"]
},
    {
  "name": "CPU2",
  "type": "cpu",
  "status": "online",
  "timestamp": "2026-06-17T07:48:32Z",
  "cpu": {"cores": 64, "load_avg": 0.07, "usage_percent": 0.1},
  "memory": {"used_mb": 6917, "total_mb": 773344, "percent": 0.9},
  "disk": {"used": "46G", "total": "879G", "percent": 6},
  "users": ["user"]
},
    {
  "name": "CPU3",
  "type": "cpu",
  "status": "online",
  "timestamp": "2026-06-17T07:48:32Z",
  "cpu": {"cores": 64, "load_avg": 0.02, "usage_percent": 0.0},
  "memory": {"used_mb": 4879, "total_mb": 773344, "percent": 0.6},
  "disk": {"used": "40G", "total": "879G", "percent": 5},
  "users": ["user"]
},
    {
  "name": "CPU4",
  "type": "cpu",
  "status": "online",
  "timestamp": "2026-06-17T07:48:32Z",
  "cpu": {"cores": 64, "load_avg": 64.32, "usage_percent": 99.7},
  "memory": {"used_mb": 412817, "total_mb": 773344, "percent": 53.4},
  "disk": {"used": "164G", "total": "879G", "percent": 20},
  "users": ["user"]
}
  ]
}
