{
  "last_updated": "2026-04-30T07:22:47Z",
  "servers": [
    {
  "name": "NIPA_server",
  "type": "gpu",
  "status": "online",
  "timestamp": "2026-04-30T07:22:47Z",
  "gpu_count": 1,
  "gpu_memory_gb": 80,
  "gpus": [{"index":0,"name":"NVIDIA H100 80GB HBM3","utilization":100,"memory_used_mb":18885,"memory_total_mb":81559,"temperature":46}],
  "cpu": {"cores": 24, "load_avg": 4.75, "usage_percent": 11.9},
  "memory": {"used_mb": 19568, "total_mb": 241600, "percent": 8.1},
  "disk": {"used": "758G", "total": "993G", "percent": 77},
  "users": ["ispl"],
  "gpu_processes": [{"pid":3987457,"name":"python","memory_mb":3938},{"pid":4089831,"name":"/home/ispl/anaconda3/envs/pnm_amgs/bin/DH_AMGS_v37","memory_mb":14932}]
},
    {
  "name": "ISPL",
  "type": "gpu",
  "status": "online",
  "timestamp": "2026-04-30T07:22:47Z",
  "gpu_count": 8,
  "gpu_memory_gb": 48,
  "gpus": [{"index":0,"name":"NVIDIA RTX A6000","utilization":52,"memory_used_mb":27517,"memory_total_mb":49140,"temperature":55},{"index":1,"name":"NVIDIA RTX A6000","utilization":68,"memory_used_mb":27517,"memory_total_mb":49140,"temperature":50},{"index":2,"name":"NVIDIA RTX A6000","utilization":0,"memory_used_mb":7135,"memory_total_mb":49140,"temperature":54},{"index":3,"name":"NVIDIA RTX A6000","utilization":0,"memory_used_mb":6419,"memory_total_mb":49140,"temperature":43},{"index":4,"name":"NVIDIA RTX A6000","utilization":3,"memory_used_mb":1999,"memory_total_mb":49140,"temperature":36},{"index":5,"name":"NVIDIA RTX A6000","utilization":79,"memory_used_mb":8454,"memory_total_mb":49140,"temperature":65},{"index":6,"name":"NVIDIA RTX A6000","utilization":56,"memory_used_mb":27517,"memory_total_mb":49140,"temperature":59},{"index":7,"name":"NVIDIA RTX A6000","utilization":46,"memory_used_mb":27517,"memory_total_mb":49140,"temperature":53}],
  "cpu": {"cores": 48, "load_avg": 27.14, "usage_percent": 21.4},
  "memory": {"used_mb": 75362, "total_mb": 709363, "percent": 10.6},
  "disk": {"used": "2.1T", "total": "3.6T", "percent": 61},
  "users": ["ispl"],
  "gpu_processes": [{"pid":1316194,"name":"/home/ispl/anaconda3/envs/mamba_esc/bin/python","memory_mb":27502},{"pid":1316195,"name":"/home/ispl/anaconda3/envs/mamba_esc/bin/python","memory_mb":27502},{"pid":1930239,"name":"python","memory_mb":8616},{"pid":1810854,"name":"python","memory_mb":7012},{"pid":1957899,"name":"python","memory_mb":2404},{"pid":1903162,"name":"python","memory_mb":2756},{"pid":1905896,"name":"python","memory_mb":5680},{"pid":1316196,"name":"/home/ispl/anaconda3/envs/mamba_esc/bin/python","memory_mb":27502},{"pid":1316197,"name":"/home/ispl/anaconda3/envs/mamba_esc/bin/python","memory_mb":27502}]
},
    {
  "name": "CPU1",
  "type": "cpu",
  "status": "online",
  "timestamp": "2026-04-30T07:22:47Z",
  "cpu": {"cores": 64, "load_avg": 0.00, "usage_percent": 0.0},
  "memory": {"used_mb": 4407, "total_mb": 773344, "percent": 0.6},
  "disk": {"used": "34G", "total": "879G", "percent": 5},
  "users": []
},
    {
  "name": "CPU2",
  "type": "cpu",
  "status": "online",
  "timestamp": "2026-04-30T07:22:47Z",
  "cpu": {"cores": 64, "load_avg": 0.02, "usage_percent": 0.1},
  "memory": {"used_mb": 6073, "total_mb": 773344, "percent": 0.8},
  "disk": {"used": "46G", "total": "879G", "percent": 6},
  "users": ["user"]
},
    {
  "name": "CPU3",
  "type": "cpu",
  "status": "online",
  "timestamp": "2026-04-30T07:22:47Z",
  "cpu": {"cores": 64, "load_avg": 0.02, "usage_percent": 0.1},
  "memory": {"used_mb": 3912, "total_mb": 773344, "percent": 0.5},
  "disk": {"used": "33G", "total": "879G", "percent": 4},
  "users": ["user"]
},
    {
  "name": "CPU4",
  "type": "cpu",
  "status": "online",
  "timestamp": "2026-04-30T07:22:47Z",
  "cpu": {"cores": 64, "load_avg": 41.43, "usage_percent": 64.3},
  "memory": {"used_mb": 21930, "total_mb": 773344, "percent": 2.8},
  "disk": {"used": "159G", "total": "879G", "percent": 20},
  "users": ["user"]
}
  ]
}
